{
  "builds": [
    {
      "build": "https://ci.chromium.org/buildbot/chromium.infra.cron/wpt-exporter/84959",
      "duration": "9 mins 17 secs",
      "info": "failed Export Chromium commits and in-flight CLs to WPT",
      "result": "Failed",
      "time": "Friday, 08-Jun-18 16:30:50 UTC"
    },
    {
      "build": "https://ci.chromium.org/buildbot/chromium.infra.cron/wpt-exporter/84958",
      "duration": "8 mins 8 secs",
      "info": "failed Export Chromium commits and in-flight CLs to WPT",
      "result": "Failed",
      "time": "Friday, 08-Jun-18 16:20:42 UTC"
    },
    {
      "build": "https://ci.chromium.org/buildbot/chromium.infra.cron/wpt-exporter/84957",
      "duration": "8 mins 20 secs",
      "info": "failed Export Chromium commits and in-flight CLs to WPT",
      "result": "Failed",
      "time": "Friday, 08-Jun-18 16:11:44 UTC"
    },
    {
      "build": "https://ci.chromium.org/buildbot/chromium.infra.cron/wpt-exporter/84956",
      "duration": "8 mins 11 secs",
      "info": "failed Export Chromium commits and in-flight CLs to WPT",
      "result": "Failed",
      "time": "Friday, 08-Jun-18 16:02:34 UTC"
    },
    {
      "build": "https://ci.chromium.org/buildbot/chromium.infra.cron/wpt-exporter/84955",
      "duration": "8 mins 24 secs",
      "info": "failed Export Chromium commits and in-flight CLs to WPT",
      "result": "Failed",
      "time": "Friday, 08-Jun-18 15:53:35 UTC"
    },
    {
      "build": "https://ci.chromium.org/buildbot/chromium.infra.cron/wpt-exporter/84954",
      "duration": "9 mins 47 secs",
      "info": "failed Export Chromium commits and in-flight CLs to WPT",
      "result": "Failed",
      "time": "Friday, 08-Jun-18 15:44:21 UTC"
    },
    {
      "build": "https://ci.chromium.org/buildbot/chromium.infra.cron/wpt-exporter/84953",
      "duration": "8 mins 16 secs",
      "info": "failed Export Chromium commits and in-flight CLs to WPT",
      "result": "Failed",
      "time": "Friday, 08-Jun-18 15:33:44 UTC"
    },
    {
      "build": "https://ci.chromium.org/buildbot/chromium.infra.cron/wpt-exporter/84952",
      "duration": "8 mins 23 secs",
      "info": "failed Export Chromium commits and in-flight CLs to WPT",
      "result": "Failed",
      "time": "Friday, 08-Jun-18 15:24:41 UTC"
    },
    {
      "build": "https://ci.chromium.org/buildbot/chromium.infra.cron/wpt-exporter/84951",
      "duration": "9 mins 37 secs",
      "info": "failed Export Chromium commits and in-flight CLs to WPT",
      "result": "Failed",
      "time": "Friday, 08-Jun-18 15:15:30 UTC"
    },
    {
      "build": "https://ci.chromium.org/buildbot/chromium.infra.cron/wpt-exporter/84950",
      "duration": "7 mins 59 secs",
      "info": "failed Export Chromium commits and in-flight CLs to WPT",
      "result": "Failed",
      "time": "Friday, 08-Jun-18 15:05:05 UTC"
    },
    {
      "build": "https://ci.chromium.org/buildbot/chromium.infra.cron/wpt-exporter/84949",
      "duration": "9 mins 43 secs",
      "info": "failed Export Chromium commits and in-flight CLs to WPT",
      "result": "Failed",
      "time": "Friday, 08-Jun-18 14:56:17 UTC"
    },
    {
      "build": "https://ci.chromium.org/buildbot/chromium.infra.cron/wpt-exporter/84948",
      "duration": "8 mins 20 secs",
      "info": "failed Export Chromium commits and in-flight CLs to WPT",
      "result": "Failed",
      "time": "Friday, 08-Jun-18 14:45:45 UTC"
    },
    {
      "build": "https://ci.chromium.org/buildbot/chromium.infra.cron/wpt-exporter/84947",
      "duration": "10 mins 13 secs",
      "info": "failed Export Chromium commits and in-flight CLs to WPT",
      "result": "Failed",
      "time": "Friday, 08-Jun-18 14:36:36 UTC"
    },
    {
      "build": "https://ci.chromium.org/buildbot/chromium.infra.cron/wpt-exporter/84946",
      "duration": "10 mins 42 secs",
      "info": "failed Export Chromium commits and in-flight CLs to WPT",
      "result": "Failed",
      "time": "Friday, 08-Jun-18 14:25:34 UTC"
    },
    {
      "build": "https://ci.chromium.org/buildbot/chromium.infra.cron/wpt-exporter/84945",
      "duration": "8 mins 48 secs",
      "info": "failed Export Chromium commits and in-flight CLs to WPT",
      "result": "Failed",
      "time": "Friday, 08-Jun-18 14:14:04 UTC"
    },
    {
      "build": "https://ci.chromium.org/buildbot/chromium.infra.cron/wpt-exporter/84944",
      "duration": "8 mins 22 secs",
      "info": "failed Export Chromium commits and in-flight CLs to WPT",
      "result": "Failed",
      "time": "Friday, 08-Jun-18 14:04:28 UTC"
    },
    {
      "build": "https://ci.chromium.org/buildbot/chromium.infra.cron/wpt-exporter/84943",
      "duration": "10 mins 14 secs",
      "info": "failed Export Chromium commits and in-flight CLs to WPT",
      "result": "Failed",
      "time": "Friday, 08-Jun-18 13:55:17 UTC"
    },
    {
      "build": "https://ci.chromium.org/buildbot/chromium.infra.cron/wpt-exporter/84942",
      "duration": "7 mins 1 secs",
      "info": "failed Export Chromium commits and in-flight CLs to WPT",
      "result": "Failed",
      "time": "Friday, 08-Jun-18 13:44:13 UTC"
    },
    {
      "build": "https://ci.chromium.org/buildbot/chromium.infra.cron/wpt-exporter/84941",
      "duration": "8 mins 27 secs",
      "info": "failed Export Chromium commits and in-flight CLs to WPT",
      "result": "Failed",
      "time": "Friday, 08-Jun-18 13:36:22 UTC"
    },
    {
      "build": "https://ci.chromium.org/buildbot/chromium.infra.cron/wpt-exporter/84940",
      "duration": "8 mins 30 secs",
      "info": "failed Export Chromium commits and in-flight CLs to WPT",
      "result": "Failed",
      "time": "Friday, 08-Jun-18 13:27:06 UTC"
    },
    {
      "build": "https://ci.chromium.org/buildbot/chromium.infra.cron/wpt-exporter/84939",
      "duration": "11 mins 49 secs",
      "info": "failed Export Chromium commits and in-flight CLs to WPT",
      "result": "Failed",
      "time": "Friday, 08-Jun-18 13:17:46 UTC"
    },
    {
      "build": "https://ci.chromium.org/buildbot/chromium.infra.cron/wpt-exporter/84938",
      "duration": "8 mins 6 secs",
      "info": "failed Export Chromium commits and in-flight CLs to WPT",
      "result": "Failed",
      "time": "Friday, 08-Jun-18 13:05:05 UTC"
    },
    {
      "build": "https://ci.chromium.org/buildbot/chromium.infra.cron/wpt-exporter/84937",
      "duration": "7 mins 44 secs",
      "info": "failed Export Chromium commits and in-flight CLs to WPT",
      "result": "Failed",
      "time": "Friday, 08-Jun-18 12:56:09 UTC"
    },
    {
      "build": "https://ci.chromium.org/buildbot/chromium.infra.cron/wpt-exporter/84936",
      "duration": "7 mins 19 secs",
      "info": "failed Export Chromium commits and in-flight CLs to WPT",
      "result": "Failed",
      "time": "Friday, 08-Jun-18 12:47:33 UTC"
    },
    {
      "build": "https://ci.chromium.org/buildbot/chromium.infra.cron/wpt-exporter/84935",
      "duration": "11 mins 33 secs",
      "info": "failed Export Chromium commits and in-flight CLs to WPT",
      "result": "Failed",
      "time": "Friday, 08-Jun-18 12:39:21 UTC"
    }
  ],
  "last_success": null,
  "recent_failures": 25
}