{
  "builds": [
    {
      "build": "https://ci.chromium.org/buildbot/chromium.infra.cron/wpt-exporter/82555",
      "duration": "8 mins 4 secs",
      "info": "build successful",
      "result": "Success",
      "time": "Thursday, 24-May-18 10:34:09 UTC"
    },
    {
      "build": "https://ci.chromium.org/buildbot/chromium.infra.cron/wpt-exporter/82554",
      "duration": "7 mins 51 secs",
      "info": "build successful",
      "result": "Success",
      "time": "Thursday, 24-May-18 10:25:11 UTC"
    },
    {
      "build": "https://ci.chromium.org/buildbot/chromium.infra.cron/wpt-exporter/82553",
      "duration": "6 mins 57 secs",
      "info": "build successful",
      "result": "Success",
      "time": "Thursday, 24-May-18 10:16:28 UTC"
    },
    {
      "build": "https://ci.chromium.org/buildbot/chromium.infra.cron/wpt-exporter/82552",
      "duration": "7 mins 47 secs",
      "info": "build successful",
      "result": "Success",
      "time": "Thursday, 24-May-18 10:08:36 UTC"
    },
    {
      "build": "https://ci.chromium.org/buildbot/chromium.infra.cron/wpt-exporter/82551",
      "duration": "7 mins 54 secs",
      "info": "build successful",
      "result": "Success",
      "time": "Thursday, 24-May-18 09:59:59 UTC"
    },
    {
      "build": "https://ci.chromium.org/buildbot/chromium.infra.cron/wpt-exporter/82550",
      "duration": "7 mins 59 secs",
      "info": "build successful",
      "result": "Success",
      "time": "Thursday, 24-May-18 09:51:14 UTC"
    },
    {
      "build": "https://ci.chromium.org/buildbot/chromium.infra.cron/wpt-exporter/82549",
      "duration": "6 mins 52 secs",
      "info": "build successful",
      "result": "Success",
      "time": "Thursday, 24-May-18 09:42:24 UTC"
    },
    {
      "build": "https://ci.chromium.org/buildbot/chromium.infra.cron/wpt-exporter/82548",
      "duration": "7 mins 36 secs",
      "info": "build successful",
      "result": "Success",
      "time": "Thursday, 24-May-18 09:34:40 UTC"
    },
    {
      "build": "https://ci.chromium.org/buildbot/chromium.infra.cron/wpt-exporter/82547",
      "duration": "7 mins 45 secs",
      "info": "build successful",
      "result": "Success",
      "time": "Thursday, 24-May-18 09:26:14 UTC"
    },
    {
      "build": "https://ci.chromium.org/buildbot/chromium.infra.cron/wpt-exporter/82546",
      "duration": "8 mins 33 secs",
      "info": "build successful",
      "result": "Success",
      "time": "Thursday, 24-May-18 09:17:38 UTC"
    },
    {
      "build": "https://ci.chromium.org/buildbot/chromium.infra.cron/wpt-exporter/82545",
      "duration": "7 mins 43 secs",
      "info": "build successful",
      "result": "Success",
      "time": "Thursday, 24-May-18 09:08:11 UTC"
    },
    {
      "build": "https://ci.chromium.org/buildbot/chromium.infra.cron/wpt-exporter/82544",
      "duration": "7 mins 55 secs",
      "info": "build successful",
      "result": "Success",
      "time": "Thursday, 24-May-18 08:59:38 UTC"
    },
    {
      "build": "https://ci.chromium.org/buildbot/chromium.infra.cron/wpt-exporter/82543",
      "duration": "9 mins 26 secs",
      "info": "build successful",
      "result": "Success",
      "time": "Thursday, 24-May-18 08:50:52 UTC"
    },
    {
      "build": "https://ci.chromium.org/buildbot/chromium.infra.cron/wpt-exporter/82542",
      "duration": "8 mins 49 secs",
      "info": "build successful",
      "result": "Success",
      "time": "Thursday, 24-May-18 08:40:33 UTC"
    },
    {
      "build": "https://ci.chromium.org/buildbot/chromium.infra.cron/wpt-exporter/82541",
      "duration": "8 mins",
      "info": "build successful",
      "result": "Success",
      "time": "Thursday, 24-May-18 08:30:52 UTC"
    },
    {
      "build": "https://ci.chromium.org/buildbot/chromium.infra.cron/wpt-exporter/82540",
      "duration": "7 mins 4 secs",
      "info": "build successful",
      "result": "Success",
      "time": "Thursday, 24-May-18 08:22:00 UTC"
    },
    {
      "build": "https://ci.chromium.org/buildbot/chromium.infra.cron/wpt-exporter/82539",
      "duration": "8 mins 5 secs",
      "info": "build successful",
      "result": "Success",
      "time": "Thursday, 24-May-18 08:14:03 UTC"
    },
    {
      "build": "https://ci.chromium.org/buildbot/chromium.infra.cron/wpt-exporter/82538",
      "duration": "7 mins 56 secs",
      "info": "build successful",
      "result": "Success",
      "time": "Thursday, 24-May-18 08:05:05 UTC"
    },
    {
      "build": "https://ci.chromium.org/buildbot/chromium.infra.cron/wpt-exporter/82537",
      "duration": "8 mins 11 secs",
      "info": "build successful",
      "result": "Success",
      "time": "Thursday, 24-May-18 07:56:16 UTC"
    },
    {
      "build": "https://ci.chromium.org/buildbot/chromium.infra.cron/wpt-exporter/82536",
      "duration": "8 mins 12 secs",
      "info": "build successful",
      "result": "Success",
      "time": "Thursday, 24-May-18 07:47:13 UTC"
    },
    {
      "build": "https://ci.chromium.org/buildbot/chromium.infra.cron/wpt-exporter/82535",
      "duration": "7 mins 5 secs",
      "info": "build successful",
      "result": "Success",
      "time": "Thursday, 24-May-18 07:38:06 UTC"
    },
    {
      "build": "https://ci.chromium.org/buildbot/chromium.infra.cron/wpt-exporter/82534",
      "duration": "8 mins",
      "info": "build successful",
      "result": "Success",
      "time": "Thursday, 24-May-18 07:30:10 UTC"
    },
    {
      "build": "https://ci.chromium.org/buildbot/chromium.infra.cron/wpt-exporter/82533",
      "duration": "6 mins 42 secs",
      "info": "build successful",
      "result": "Success",
      "time": "Thursday, 24-May-18 07:21:18 UTC"
    },
    {
      "build": "https://ci.chromium.org/buildbot/chromium.infra.cron/wpt-exporter/82532",
      "duration": "6 mins 52 secs",
      "info": "build successful",
      "result": "Success",
      "time": "Thursday, 24-May-18 07:13:44 UTC"
    },
    {
      "build": "https://ci.chromium.org/buildbot/chromium.infra.cron/wpt-exporter/82531",
      "duration": "6 mins 43 secs",
      "info": "build successful",
      "result": "Success",
      "time": "Thursday, 24-May-18 07:06:01 UTC"
    }
  ],
  "last_success": "Thursday, 24-May-18 10:34:09 UTC",
  "recent_failures": 0
}