{
  "builds": [
    {
      "build": "https://ci.chromium.org/buildbot/chromium.infra.cron/wpt-importer/23624",
      "duration": "9 mins 58 secs",
      "info": "build successful",
      "result": "Success",
      "time": "Thursday, 30-Aug-18 07:00:47 UTC"
    },
    {
      "build": "https://ci.chromium.org/buildbot/chromium.infra.cron/wpt-importer/23623",
      "duration": "10 mins 16 secs",
      "info": "build successful",
      "result": "Success",
      "time": "Thursday, 30-Aug-18 06:49:57 UTC"
    },
    {
      "build": "https://ci.chromium.org/buildbot/chromium.infra.cron/wpt-importer/23622",
      "duration": "10 mins 2 secs",
      "info": "build successful",
      "result": "Success",
      "time": "Thursday, 30-Aug-18 06:38:44 UTC"
    },
    {
      "build": "https://ci.chromium.org/buildbot/chromium.infra.cron/wpt-importer/23621",
      "duration": "10 mins 17 secs",
      "info": "build successful",
      "result": "Success",
      "time": "Thursday, 30-Aug-18 06:27:46 UTC"
    },
    {
      "build": "https://ci.chromium.org/buildbot/chromium.infra.cron/wpt-importer/23620",
      "duration": "10 mins 3 secs",
      "info": "build successful",
      "result": "Success",
      "time": "Thursday, 30-Aug-18 06:16:31 UTC"
    },
    {
      "build": "https://ci.chromium.org/buildbot/chromium.infra.cron/wpt-importer/23619",
      "duration": "10 mins 16 secs",
      "info": "build successful",
      "result": "Success",
      "time": "Thursday, 30-Aug-18 06:05:35 UTC"
    },
    {
      "build": "https://ci.chromium.org/buildbot/chromium.infra.cron/wpt-importer/23618",
      "duration": "10 mins 3 secs",
      "info": "build successful",
      "result": "Success",
      "time": "Thursday, 30-Aug-18 05:54:24 UTC"
    },
    {
      "build": "https://ci.chromium.org/buildbot/chromium.infra.cron/wpt-importer/23617",
      "duration": "10 mins 10 secs",
      "info": "build successful",
      "result": "Success",
      "time": "Thursday, 30-Aug-18 05:43:26 UTC"
    },
    {
      "build": "https://ci.chromium.org/buildbot/chromium.infra.cron/wpt-importer/23616",
      "duration": "10 mins 10 secs",
      "info": "build successful",
      "result": "Success",
      "time": "Thursday, 30-Aug-18 05:32:19 UTC"
    },
    {
      "build": "https://ci.chromium.org/buildbot/chromium.infra.cron/wpt-importer/23615",
      "duration": "10 mins 8 secs",
      "info": "build successful",
      "result": "Success",
      "time": "Thursday, 30-Aug-18 05:21:11 UTC"
    },
    {
      "build": "https://ci.chromium.org/buildbot/chromium.infra.cron/wpt-importer/23614",
      "duration": "9 mins 54 secs",
      "info": "build successful",
      "result": "Success",
      "time": "Thursday, 30-Aug-18 05:10:08 UTC"
    },
    {
      "build": "https://ci.chromium.org/buildbot/chromium.infra.cron/wpt-importer/23613",
      "duration": "10 mins 13 secs",
      "info": "build successful",
      "result": "Success",
      "time": "Thursday, 30-Aug-18 04:59:17 UTC"
    },
    {
      "build": "https://ci.chromium.org/buildbot/chromium.infra.cron/wpt-importer/23612",
      "duration": "2 hrs 16 mins",
      "info": "build successful",
      "result": "Success",
      "time": "Thursday, 30-Aug-18 04:48:07 UTC"
    },
    {
      "build": "https://ci.chromium.org/buildbot/chromium.infra.cron/wpt-importer/23611",
      "duration": "4 hrs 17 mins",
      "info": "build successful",
      "result": "Success",
      "time": "Thursday, 30-Aug-18 02:30:18 UTC"
    },
    {
      "build": "https://ci.chromium.org/buildbot/chromium.infra.cron/wpt-importer/23610",
      "duration": "9 mins 58 secs",
      "info": "build successful",
      "result": "Success",
      "time": "Wednesday, 29-Aug-18 22:11:19 UTC"
    },
    {
      "build": "https://ci.chromium.org/buildbot/chromium.infra.cron/wpt-importer/23609",
      "duration": "10 mins 4 secs",
      "info": "build successful",
      "result": "Success",
      "time": "Wednesday, 29-Aug-18 22:00:24 UTC"
    },
    {
      "build": "https://ci.chromium.org/buildbot/chromium.infra.cron/wpt-importer/23608",
      "duration": "10 mins 9 secs",
      "info": "build successful",
      "result": "Success",
      "time": "Wednesday, 29-Aug-18 21:49:25 UTC"
    },
    {
      "build": "https://ci.chromium.org/buildbot/chromium.infra.cron/wpt-importer/23607",
      "duration": "10 mins 7 secs",
      "info": "build successful",
      "result": "Success",
      "time": "Wednesday, 29-Aug-18 21:38:15 UTC"
    },
    {
      "build": "https://ci.chromium.org/buildbot/chromium.infra.cron/wpt-importer/23606",
      "duration": "10 mins 10 secs",
      "info": "build successful",
      "result": "Success",
      "time": "Wednesday, 29-Aug-18 21:27:14 UTC"
    },
    {
      "build": "https://ci.chromium.org/buildbot/chromium.infra.cron/wpt-importer/23605",
      "duration": "10 mins 27 secs",
      "info": "build successful",
      "result": "Success",
      "time": "Wednesday, 29-Aug-18 21:16:00 UTC"
    },
    {
      "build": "https://ci.chromium.org/buildbot/chromium.infra.cron/wpt-importer/23604",
      "duration": "11 mins 2 secs",
      "info": "build successful",
      "result": "Success",
      "time": "Wednesday, 29-Aug-18 21:04:38 UTC"
    },
    {
      "build": "https://ci.chromium.org/buildbot/chromium.infra.cron/wpt-importer/23603",
      "duration": "10 mins 33 secs",
      "info": "build successful",
      "result": "Success",
      "time": "Wednesday, 29-Aug-18 20:52:18 UTC"
    },
    {
      "build": "https://ci.chromium.org/buildbot/chromium.infra.cron/wpt-importer/23602",
      "duration": "10 mins 46 secs",
      "info": "build successful",
      "result": "Success",
      "time": "Wednesday, 29-Aug-18 20:40:45 UTC"
    },
    {
      "build": "https://ci.chromium.org/buildbot/chromium.infra.cron/wpt-importer/23601",
      "duration": "10 mins 37 secs",
      "info": "build successful",
      "result": "Success",
      "time": "Wednesday, 29-Aug-18 20:29:00 UTC"
    },
    {
      "build": "https://ci.chromium.org/buildbot/chromium.infra.cron/wpt-importer/23600",
      "duration": "12 mins 49 secs",
      "info": "build successful",
      "result": "Success",
      "time": "Wednesday, 29-Aug-18 20:17:30 UTC"
    }
  ],
  "last_success": "Thursday, 30-Aug-18 07:00:47 UTC",
  "recent_failures": 0
}