{
  "builds": [
    {
      "build": "https://ci.chromium.org/buildbot/chromium.infra.cron/wpt-importer/16432",
      "duration": "10 mins 6 secs",
      "info": "build successful",
      "result": "Success",
      "time": "Sunday, 29-Apr-18 10:37:24 UTC"
    },
    {
      "build": "https://ci.chromium.org/buildbot/chromium.infra.cron/wpt-importer/16431",
      "duration": "10 mins 14 secs",
      "info": "build successful",
      "result": "Success",
      "time": "Sunday, 29-Apr-18 10:26:04 UTC"
    },
    {
      "build": "https://ci.chromium.org/buildbot/chromium.infra.cron/wpt-importer/16430",
      "duration": "9 mins 56 secs",
      "info": "build successful",
      "result": "Success",
      "time": "Sunday, 29-Apr-18 10:14:34 UTC"
    },
    {
      "build": "https://ci.chromium.org/buildbot/chromium.infra.cron/wpt-importer/16429",
      "duration": "10 mins 51 secs",
      "info": "build successful",
      "result": "Success",
      "time": "Sunday, 29-Apr-18 10:03:23 UTC"
    },
    {
      "build": "https://ci.chromium.org/buildbot/chromium.infra.cron/wpt-importer/16428",
      "duration": "11 mins",
      "info": "build successful",
      "result": "Success",
      "time": "Sunday, 29-Apr-18 09:51:18 UTC"
    },
    {
      "build": "https://ci.chromium.org/buildbot/chromium.infra.cron/wpt-importer/16427",
      "duration": "10 mins 14 secs",
      "info": "build successful",
      "result": "Success",
      "time": "Sunday, 29-Apr-18 09:39:02 UTC"
    },
    {
      "build": "https://ci.chromium.org/buildbot/chromium.infra.cron/wpt-importer/16426",
      "duration": "10 mins 2 secs",
      "info": "build successful",
      "result": "Success",
      "time": "Sunday, 29-Apr-18 09:27:33 UTC"
    },
    {
      "build": "https://ci.chromium.org/buildbot/chromium.infra.cron/wpt-importer/16425",
      "duration": "10 mins 5 secs",
      "info": "build successful",
      "result": "Success",
      "time": "Sunday, 29-Apr-18 09:16:16 UTC"
    },
    {
      "build": "https://ci.chromium.org/buildbot/chromium.infra.cron/wpt-importer/16424",
      "duration": "10 mins 7 secs",
      "info": "build successful",
      "result": "Success",
      "time": "Sunday, 29-Apr-18 09:04:57 UTC"
    },
    {
      "build": "https://ci.chromium.org/buildbot/chromium.infra.cron/wpt-importer/16423",
      "duration": "10 mins 13 secs",
      "info": "build successful",
      "result": "Success",
      "time": "Sunday, 29-Apr-18 08:53:36 UTC"
    },
    {
      "build": "https://ci.chromium.org/buildbot/chromium.infra.cron/wpt-importer/16422",
      "duration": "10 mins 6 secs",
      "info": "build successful",
      "result": "Success",
      "time": "Sunday, 29-Apr-18 08:42:09 UTC"
    },
    {
      "build": "https://ci.chromium.org/buildbot/chromium.infra.cron/wpt-importer/16421",
      "duration": "10 mins 10 secs",
      "info": "build successful",
      "result": "Success",
      "time": "Sunday, 29-Apr-18 08:30:48 UTC"
    },
    {
      "build": "https://ci.chromium.org/buildbot/chromium.infra.cron/wpt-importer/16420",
      "duration": "10 mins 7 secs",
      "info": "build successful",
      "result": "Success",
      "time": "Sunday, 29-Apr-18 08:19:24 UTC"
    },
    {
      "build": "https://ci.chromium.org/buildbot/chromium.infra.cron/wpt-importer/16419",
      "duration": "10 mins 6 secs",
      "info": "build successful",
      "result": "Success",
      "time": "Sunday, 29-Apr-18 08:08:02 UTC"
    },
    {
      "build": "https://ci.chromium.org/buildbot/chromium.infra.cron/wpt-importer/16418",
      "duration": "10 mins 9 secs",
      "info": "build successful",
      "result": "Success",
      "time": "Sunday, 29-Apr-18 07:56:41 UTC"
    },
    {
      "build": "https://ci.chromium.org/buildbot/chromium.infra.cron/wpt-importer/16417",
      "duration": "10 mins 10 secs",
      "info": "build successful",
      "result": "Success",
      "time": "Sunday, 29-Apr-18 07:45:17 UTC"
    },
    {
      "build": "https://ci.chromium.org/buildbot/chromium.infra.cron/wpt-importer/16416",
      "duration": "10 mins 5 secs",
      "info": "build successful",
      "result": "Success",
      "time": "Sunday, 29-Apr-18 07:33:52 UTC"
    },
    {
      "build": "https://ci.chromium.org/buildbot/chromium.infra.cron/wpt-importer/16415",
      "duration": "10 mins 13 secs",
      "info": "build successful",
      "result": "Success",
      "time": "Sunday, 29-Apr-18 07:22:32 UTC"
    },
    {
      "build": "https://ci.chromium.org/buildbot/chromium.infra.cron/wpt-importer/16414",
      "duration": "10 mins 14 secs",
      "info": "build successful",
      "result": "Success",
      "time": "Sunday, 29-Apr-18 07:09:06 UTC"
    },
    {
      "build": "https://ci.chromium.org/buildbot/chromium.infra.cron/wpt-importer/16413",
      "duration": "10 mins 5 secs",
      "info": "build successful",
      "result": "Success",
      "time": "Sunday, 29-Apr-18 06:57:32 UTC"
    },
    {
      "build": "https://ci.chromium.org/buildbot/chromium.infra.cron/wpt-importer/16412",
      "duration": "10 mins 42 secs",
      "info": "build successful",
      "result": "Success",
      "time": "Sunday, 29-Apr-18 06:46:12 UTC"
    },
    {
      "build": "https://ci.chromium.org/buildbot/chromium.infra.cron/wpt-importer/16411",
      "duration": "10 mins 55 secs",
      "info": "build successful",
      "result": "Success",
      "time": "Sunday, 29-Apr-18 06:34:16 UTC"
    },
    {
      "build": "https://ci.chromium.org/buildbot/chromium.infra.cron/wpt-importer/16410",
      "duration": "10 mins 3 secs",
      "info": "build successful",
      "result": "Success",
      "time": "Sunday, 29-Apr-18 06:22:06 UTC"
    },
    {
      "build": "https://ci.chromium.org/buildbot/chromium.infra.cron/wpt-importer/16409",
      "duration": "10 mins 15 secs",
      "info": "build successful",
      "result": "Success",
      "time": "Sunday, 29-Apr-18 06:10:50 UTC"
    },
    {
      "build": "https://ci.chromium.org/buildbot/chromium.infra.cron/wpt-importer/16408",
      "duration": "10 mins 20 secs",
      "info": "build successful",
      "result": "Success",
      "time": "Sunday, 29-Apr-18 05:59:21 UTC"
    }
  ],
  "last_success": "Sunday, 29-Apr-18 10:37:24 UTC",
  "recent_failures": 0
}