{
  "builds": [
    {
      "build": "https://ci.chromium.org/buildbot/chromium.infra.cron/wpt-importer/15769",
      "duration": "11 mins 2 secs",
      "info": "build successful",
      "result": "Success",
      "time": "Wednesday, 18-Apr-18 18:10:45 UTC"
    },
    {
      "build": "https://ci.chromium.org/buildbot/chromium.infra.cron/wpt-importer/15768",
      "duration": "11 mins 5 secs",
      "info": "build successful",
      "result": "Success",
      "time": "Wednesday, 18-Apr-18 17:58:26 UTC"
    },
    {
      "build": "https://ci.chromium.org/buildbot/chromium.infra.cron/wpt-importer/15767",
      "duration": "11 mins 7 secs",
      "info": "build successful",
      "result": "Success",
      "time": "Wednesday, 18-Apr-18 17:46:05 UTC"
    },
    {
      "build": "https://ci.chromium.org/buildbot/chromium.infra.cron/wpt-importer/15766",
      "duration": "11 mins 8 secs",
      "info": "build successful",
      "result": "Success",
      "time": "Wednesday, 18-Apr-18 17:33:43 UTC"
    },
    {
      "build": "https://ci.chromium.org/buildbot/chromium.infra.cron/wpt-importer/15765",
      "duration": "11 mins 13 secs",
      "info": "build successful",
      "result": "Success",
      "time": "Wednesday, 18-Apr-18 17:21:19 UTC"
    },
    {
      "build": "https://ci.chromium.org/buildbot/chromium.infra.cron/wpt-importer/15764",
      "duration": "11 mins 12 secs",
      "info": "build successful",
      "result": "Success",
      "time": "Wednesday, 18-Apr-18 17:08:51 UTC"
    },
    {
      "build": "https://ci.chromium.org/buildbot/chromium.infra.cron/wpt-importer/15763",
      "duration": "11 mins 6 secs",
      "info": "build successful",
      "result": "Success",
      "time": "Wednesday, 18-Apr-18 16:56:25 UTC"
    },
    {
      "build": "https://ci.chromium.org/buildbot/chromium.infra.cron/wpt-importer/15762",
      "duration": "11 mins 7 secs",
      "info": "build successful",
      "result": "Success",
      "time": "Wednesday, 18-Apr-18 16:43:57 UTC"
    },
    {
      "build": "https://ci.chromium.org/buildbot/chromium.infra.cron/wpt-importer/15761",
      "duration": "10 mins 54 secs",
      "info": "build successful",
      "result": "Success",
      "time": "Wednesday, 18-Apr-18 16:31:35 UTC"
    },
    {
      "build": "https://ci.chromium.org/buildbot/chromium.infra.cron/wpt-importer/15760",
      "duration": "10 mins 58 secs",
      "info": "build successful",
      "result": "Success",
      "time": "Wednesday, 18-Apr-18 16:19:26 UTC"
    },
    {
      "build": "https://ci.chromium.org/buildbot/chromium.infra.cron/wpt-importer/15759",
      "duration": "12 mins 35 secs",
      "info": "build successful",
      "result": "Success",
      "time": "Wednesday, 18-Apr-18 16:07:13 UTC"
    },
    {
      "build": "https://ci.chromium.org/buildbot/chromium.infra.cron/wpt-importer/15758",
      "duration": "11 mins 5 secs",
      "info": "build successful",
      "result": "Success",
      "time": "Wednesday, 18-Apr-18 15:53:23 UTC"
    },
    {
      "build": "https://ci.chromium.org/buildbot/chromium.infra.cron/wpt-importer/15757",
      "duration": "11 mins 21 secs",
      "info": "build successful",
      "result": "Success",
      "time": "Wednesday, 18-Apr-18 15:41:03 UTC"
    },
    {
      "build": "https://ci.chromium.org/buildbot/chromium.infra.cron/wpt-importer/15756",
      "duration": "10 mins 55 secs",
      "info": "build successful",
      "result": "Success",
      "time": "Wednesday, 18-Apr-18 15:28:28 UTC"
    },
    {
      "build": "https://ci.chromium.org/buildbot/chromium.infra.cron/wpt-importer/15755",
      "duration": "11 mins 12 secs",
      "info": "build successful",
      "result": "Success",
      "time": "Wednesday, 18-Apr-18 15:16:19 UTC"
    },
    {
      "build": "https://ci.chromium.org/buildbot/chromium.infra.cron/wpt-importer/15754",
      "duration": "2 hrs 26 mins",
      "info": "build successful",
      "result": "Success",
      "time": "Wednesday, 18-Apr-18 15:01:50 UTC"
    },
    {
      "build": "https://ci.chromium.org/buildbot/chromium.infra.cron/wpt-importer/15753",
      "duration": "2 hrs 19 mins",
      "info": "build successful",
      "result": "Success",
      "time": "Wednesday, 18-Apr-18 12:34:29 UTC"
    },
    {
      "build": "https://ci.chromium.org/buildbot/chromium.infra.cron/wpt-importer/15752",
      "duration": "2 hrs 10 mins",
      "info": "build successful",
      "result": "Success",
      "time": "Wednesday, 18-Apr-18 10:13:58 UTC"
    },
    {
      "build": "https://ci.chromium.org/buildbot/chromium.infra.cron/wpt-importer/15751",
      "duration": "11 mins 11 secs",
      "info": "build successful",
      "result": "Success",
      "time": "Wednesday, 18-Apr-18 08:01:47 UTC"
    },
    {
      "build": "https://ci.chromium.org/buildbot/chromium.infra.cron/wpt-importer/15750",
      "duration": "10 mins 59 secs",
      "info": "build successful",
      "result": "Success",
      "time": "Wednesday, 18-Apr-18 07:49:21 UTC"
    },
    {
      "build": "https://ci.chromium.org/buildbot/chromium.infra.cron/wpt-importer/15749",
      "duration": "11 mins 9 secs",
      "info": "build successful",
      "result": "Success",
      "time": "Wednesday, 18-Apr-18 07:37:05 UTC"
    },
    {
      "build": "https://ci.chromium.org/buildbot/chromium.infra.cron/wpt-importer/15748",
      "duration": "11 mins 5 secs",
      "info": "build successful",
      "result": "Success",
      "time": "Wednesday, 18-Apr-18 07:24:41 UTC"
    },
    {
      "build": "https://ci.chromium.org/buildbot/chromium.infra.cron/wpt-importer/15747",
      "duration": "10 mins 21 secs",
      "info": "build successful",
      "result": "Success",
      "time": "Wednesday, 18-Apr-18 07:10:24 UTC"
    },
    {
      "build": "https://ci.chromium.org/buildbot/chromium.infra.cron/wpt-importer/15746",
      "duration": "13 mins 32 secs",
      "info": "build successful",
      "result": "Success",
      "time": "Wednesday, 18-Apr-18 06:58:48 UTC"
    },
    {
      "build": "https://ci.chromium.org/buildbot/chromium.infra.cron/wpt-importer/15745",
      "duration": "11 mins 6 secs",
      "info": "build successful",
      "result": "Success",
      "time": "Wednesday, 18-Apr-18 06:44:01 UTC"
    }
  ],
  "last_success": "Wednesday, 18-Apr-18 18:10:45 UTC",
  "recent_failures": 0
}